README.rst
setup.cfg
setup.py
bin/ci-yml
ci-yml/__init__.py
ci_yml/__init__.py
ci_yml.egg-info/PKG-INFO
ci_yml.egg-info/SOURCES.txt
ci_yml.egg-info/dependency_links.txt
ci_yml.egg-info/requires.txt
ci_yml.egg-info/top_level.txt