Metadata-Version: 1.1
Name: ci-yml
Version: 0.3
Summary: A .ci.yml parser for Gitlab-CI
Home-page: http://github.com/claudyus/ci-yml
Author: Claudio Mignanti
Author-email: c.mignanti[at]gmail[dot]com
License: MIT
Download-URL: https://github.com/claudyus/ci-yml/tarball/0.3
Platform: UNKNOWN
